wnm/__init__.py
wnm/__main__.py
wnm/actions.py
wnm/common.py
wnm/config.py
wnm/db_migration.py
wnm/decision_engine.py
wnm/executor.py
wnm/migration.py
wnm/models.py
wnm/reports.py
wnm/utils.py
wnm/wallets.py
wnm/firewall/__init__.py
wnm/firewall/base.py
wnm/firewall/factory.py
wnm/firewall/null_firewall.py
wnm/firewall/ufw_manager.py
wnm/process_managers/__init__.py
wnm/process_managers/antctl_manager.py
wnm/process_managers/antctl_zen_manager.py
wnm/process_managers/base.py
wnm/process_managers/docker_manager.py
wnm/process_managers/factory.py
wnm/process_managers/launchd_manager.py
wnm/process_managers/setsid_manager.py
wnm/process_managers/systemd_manager.py
wnm-0.4.1.dist-info/METADATA
wnm-0.4.1.dist-info/WHEEL
wnm-0.4.1.dist-info/entry_points.txt
wnm-0.4.1.dist-info/top_level.txt
wnm-0.4.1.dist-info/RECORD
