Metadata-Version: 2.4
Name: wnm
Version: 0.4.1
Summary: Manager for Autonomi nodes
Author-email: Troy Johnson <troy@weave.sh>
License: GPL-3.0
Project-URL: Repository, https://github.com/iweave/weave-node-manager.git
Project-URL: Issues, https://github.com/iweave/weave-node-manager/issues
Keywords: Autonomi,antnode,weave,xd7
Classifier: Development Status :: 3 - Alpha
Classifier: Environment :: Console
Classifier: Intended Audience :: Developers
Classifier: License :: OSI Approved :: GNU General Public License v3 (GPLv3)
Classifier: Operating System :: POSIX :: Linux
Classifier: Programming Language :: Python :: 3.12
Classifier: Topic :: Software Development :: Libraries :: Python Modules
Classifier: Topic :: System :: Distributed Computing
Requires-Python: >=3.12.3
Requires-Dist: python-dotenv
Requires-Dist: requests
Requires-Dist: packaging
Requires-Dist: sqlalchemy
Requires-Dist: alembic
Requires-Dist: json-fix
Requires-Dist: psutil
Requires-Dist: configargparse
Provides-Extra: dev
Requires-Dist: black; extra == "dev"
Requires-Dist: isort; extra == "dev"
Requires-Dist: build; extra == "dev"
Requires-Dist: twine; extra == "dev"
Requires-Dist: pytest>=8.0.0; extra == "dev"
Requires-Dist: pytest-cov>=4.1.0; extra == "dev"
Requires-Dist: pytest-asyncio>=0.23.0; extra == "dev"
Requires-Dist: pytest-mock>=3.12.0; extra == "dev"
Requires-Dist: pytest-docker>=3.1.0; extra == "dev"
Requires-Dist: docker>=7.0.0; extra == "dev"
